mcp_monday_server/__init__.py
mcp_monday_server/common.py
mcp_monday_server/resources.py
mcp_monday_server/server.py
mcp_monday_server/tools.py
mcp_monday_server-0.1.1.dist-info/METADATA
mcp_monday_server-0.1.1.dist-info/WHEEL
mcp_monday_server-0.1.1.dist-info/entry_points.txt
mcp_monday_server-0.1.1.dist-info/licenses/LICENSE
mcp_monday_server-0.1.1.dist-info/RECORD
