Metadata-Version: 2.4
Name: mcp-monday-server
Version: 0.1.1
Summary: Basic MCP Server ot integrate with monday
Project-URL: Homepage, https://github.com/Sofias-ai/mcp-server-monday/
Author: sofias tech
License-File: LICENSE
Requires-Python: >=3.10
Requires-Dist: mcp>=1.2.1
Requires-Dist: monday>=2.0.1
Requires-Dist: python-dotenv>=1.0.0
Requires-Dist: requests>=2.32.3
